Metadata-Version: 1.0
Name: my-first-package1234
Version: 0.1
Summary: Gaussian & Binomial Distributions
Home-page: UNKNOWN
Author: Maya Screen
Author-email: UNKNOWN
License: UNKNOWN
Platform: UNKNOWN
